AUTHORS.rst
CONTRIBUTING.rst
HISTORY.rst
LICENSE
MANIFEST.in
README.rst
setup.cfg
setup.py
django_users2.egg-info/PKG-INFO
django_users2.egg-info/SOURCES.txt
django_users2.egg-info/dependency_links.txt
django_users2.egg-info/not-zip-safe
django_users2.egg-info/requires.txt
django_users2.egg-info/top_level.txt
users/__init__.py
users/admin.py
users/compat.py
users/conf.py
users/fields.py
users/forms.py
users/managers.py
users/models.py
users/signals.py
users/urls.py
users/utils.py
users/views.py
users/templates/base.html
users/templates/users/activate.html
users/templates/users/activation_complete.html
users/templates/users/activation_email.html
users/templates/users/activation_email_subject.html
users/templates/users/login.html
users/templates/users/logout.html
users/templates/users/password_change_done.html
users/templates/users/password_change_form.html
users/templates/users/password_reset_complete.html
users/templates/users/password_reset_confirm.html
users/templates/users/password_reset_done.html
users/templates/users/password_reset_email.html
users/templates/users/password_reset_form.html
users/templates/users/password_reset_subject.html
users/templates/users/registration_closed.html
users/templates/users/registration_complete.html
users/templates/users/registration_form.html
users/templates/users/partials/errors.html
users/templates/users/partials/field.html
users/templates/users/partials/honeypot.html
users/templatetags/__init__.py
users/templatetags/form_tags.py