Metadata-Version: 1.1
Name: django-users2
Version: 0.1.12
Summary: Custom user model for django >=1.5 with support for multiple user types
Home-page: https://github.com/mishbahr/django-users2
Author: Mishbah Razzaque
Author-email: mishbahx@gmail.com
License: BSD
Keywords: django-users2
Platform: UNKNOWN
Classifier: Development Status :: 3 - Alpha
Classifier: Framework :: Django
Classifier: Intended Audience :: Developers
Classifier: License :: OSI Approved :: BSD License
Classifier: Natural Language :: English
Classifier: Programming Language :: Python :: 2
Classifier: Programming Language :: Python :: 2.6
Classifier: Programming Language :: Python :: 2.7
Classifier: Programming Language :: Python :: 3
Classifier: Programming Language :: Python :: 3.3
